sphinx_github_changelog/__init__.py
sphinx_github_changelog/changelog.py
sphinx_github_changelog/credentials.py
sphinx_github_changelog/urls.py
sphinx_github_changelog-1.7.0.dist-info/METADATA
sphinx_github_changelog-1.7.0.dist-info/WHEEL
sphinx_github_changelog-1.7.0.dist-info/licenses/LICENSE
sphinx_github_changelog-1.7.0.dist-info/RECORD
