Metadata-Version: 2.4
Name: sphinx-github-changelog
Version: 1.7.0
Summary: Build a sphinx changelog from GitHub Releases
Project-URL: Homepage, https://sphinx-github-changelog.readthedocs.io/en/latest/
Project-URL: Repository, https://github.com/ewjoachim/sphinx-github-changelog
Project-URL: Documentation, https://sphinx-github-changelog.readthedocs.io/en/latest/
Author-email: Joachim Jablon <ewjoachim@gmail.com>
License-Expression: MIT
License-File: LICENSE
Keywords: changelog,github,releases,sphinx
Classifier: Framework :: Sphinx
Classifier: Framework :: Sphinx :: Extension
Classifier: Programming Language :: Python :: 3.9
Classifier: Programming Language :: Python :: 3.10
Classifier: Programming Language :: Python :: 3.11
Classifier: Programming Language :: Python :: 3.12
Classifier: Programming Language :: Python :: 3.13
Classifier: Topic :: Documentation
Classifier: Topic :: Documentation :: Sphinx
Classifier: Typing :: Typed
Requires-Python: >=3.9
Requires-Dist: docutils
Requires-Dist: requests
Requires-Dist: sphinx
